{ "application_group_id": "3mavyiwf", "application_id": "gj8nhgir", "timestamp": 1570221600, "utc_timestamp": "2019-10-04T20:40:00.038Z", "type": "incident", "incident": { "incident_id": "fed6b7bf-f741-49d1-ab36-5d04e9a5c005", "title": "[Instana] RobotShop call rate is too high - RobotShop call rate stays at a high level for an extended period of time", "description": "MySQL Database is unavailable in App.", "created_at": "2019-09-11T06:39:48.000Z", "updated_at": "2019-09-11T07:57:58.000Z", "resolved_at": "2019-09-11T07:57:58.000Z", "closed_at": "2019-09-11T07:57:58.000Z", "started_at": "2019-09-11T07:57:58.000Z", "business_duration_ms": 15347, "severity": 1, "priority": 2, "impact": 3, "state": "new", "source": { "source_name": "GitHub", "source_url": "https://pirsoscom.github.io/git-robotshop.html", "source_incident_id":  "ROB0000164", "source_application_id": "tokenizer124" }, "comments": [{ "comment_text": "MySQL Deployment was out of Memory. Resolved by increasing memory and restarting mysql pod: oc delete pod -n robot-shop $(oc get po -n robot-shop|grep mysql|awk '{print$1}')" }], "resolution": { "rca_id": "RCA004013505", "resolution_summary": "MySQL Deployment was out of Memory. Resolved by increasing memory and restarting mysql pod: oc delete pod -n robot-shop $(oc get po -n robot-shop|grep mysql|awk '{print$1}')" }, "features": [] }, "meta_features": []}
{ "application_group_id": "3mavyiwf", "application_id": "gj8nhgir", "timestamp": 1570221600, "utc_timestamp": "2019-10-04T20:40:00.038Z", "type": "incident", "incident": { "incident_id": "fed6b7bf-f741-49d1-ab36-5d04e9a5c005", "title": "[Instana] RobotShop sudden increase in the number of erroneous calls - This can be a sign of a problem on one side of the connection", "description": "MySQL Database is unavailable in App.", "created_at": "2019-09-11T06:39:48.000Z", "updated_at": "2019-09-11T07:57:58.000Z", "resolved_at": "2019-09-11T07:57:58.000Z", "closed_at": "2019-09-11T07:57:58.000Z", "started_at": "2019-09-11T07:57:58.000Z", "business_duration_ms": 15347, "severity": 1, "priority": 2, "impact": 3, "state": "new", "source": { "source_name": "GitHub", "source_url": "https://pirsoscom.github.io/git-robotshop.html", "source_incident_id":  "ROB0000164", "source_application_id": "tokenizer124" }, "comments": [{ "comment_text": "MySQL Deployment was out of Memory. Resolved by increasing memory and restarting mysql pod: oc delete pod -n robot-shop $(oc get po -n robot-shop|grep mysql|awk '{print$1}')" }], "resolution": { "rca_id": "RCA004013505", "resolution_summary": "MySQL Deployment was out of Memory. Resolved by increasing memory and restarting mysql pod: oc delete pod -n robot-shop $(oc get po -n robot-shop|grep mysql|awk '{print$1}')" }, "features": [] }, "meta_features": []}
{ "application_group_id": "3mavyiwf", "application_id": "gj8nhgir", "timestamp": 1570221600, "utc_timestamp": "2019-10-04T20:40:00.038Z", "type": "incident", "incident": { "incident_id": "fed6b7bf-f741-49d1-ab36-5d04e9a5c005", "title": "[Instana] RobotShop call rate is too high - RobotShop call rate stays at a high level for an extended period of time", "description": "MySQL Database is unavailable in App.", "created_at": "2019-09-11T06:39:48.000Z", "updated_at": "2019-09-11T07:57:58.000Z", "resolved_at": "2019-09-11T07:57:58.000Z", "closed_at": "2019-09-11T07:57:58.000Z", "started_at": "2019-09-11T07:57:58.000Z", "business_duration_ms": 15347, "severity": 1, "priority": 2, "impact": 3, "state": "new", "source": { "source_name": "GitHub", "source_url": "https://pirsoscom.github.io/git-robotshop.html", "source_incident_id":  "ROB0000164", "source_application_id": "tokenizer124" }, "comments": [{ "comment_text": "MySQL Deployment was out of Memory. Resolved by increasing memory and restarting mysql pod: oc delete pod -n robot-shop $(oc get po -n robot-shop|grep mysql|awk '{print$1}')" }], "resolution": { "rca_id": "RCA004013505", "resolution_summary": "MySQL Deployment was out of Memory. Resolved by increasing memory and restarting mysql pod: oc delete pod -n robot-shop $(oc get po -n robot-shop|grep mysql|awk '{print$1}')" }, "features": [] }, "meta_features": []}
{ "application_group_id": "3mavyiwf", "application_id": "gj8nhgir", "timestamp": 1570221600, "utc_timestamp": "2019-10-04T20:40:00.038Z", "type": "incident", "incident": { "incident_id": "fed6b7bf-f741-49d1-ab36-5d04e9a5c005", "title": "[Instana] RobotShop call rate is too high - RobotShop call rate stays at a high level for an extended period of time", "description": "MySQL Database is unavailable in App.", "created_at": "2019-09-11T06:39:48.000Z", "updated_at": "2019-09-11T07:57:58.000Z", "resolved_at": "2019-09-11T07:57:58.000Z", "closed_at": "2019-09-11T07:57:58.000Z", "started_at": "2019-09-11T07:57:58.000Z", "business_duration_ms": 15347, "severity": 1, "priority": 2, "impact": 3, "state": "new", "source": { "source_name": "GitHub", "source_url": "https://pirsoscom.github.io/git-robotshop.html", "source_incident_id":  "ROB0000164", "source_application_id": "tokenizer124" }, "comments": [{ "comment_text": "MySQL Deployment was out of Memory. Resolved by increasing memory and restarting mysql pod: oc delete pod -n robot-shop $(oc get po -n robot-shop|grep mysql|awk '{print$1}')" }], "resolution": { "rca_id": "RCA004013505", "resolution_summary": "MySQL Deployment was out of Memory. Resolved by increasing memory and restarting mysql pod: oc delete pod -n robot-shop $(oc get po -n robot-shop|grep mysql|awk '{print$1}')" }, "features": [] }, "meta_features": []}
{ "application_group_id": "3mavyiwf", "application_id": "gj8nhgir", "timestamp": 1570221600, "utc_timestamp": "2019-10-04T20:40:00.038Z", "type": "incident", "incident": { "incident_id": "fed6b7bf-f741-49d1-ab36-5d04e9a5c005", "title": "[Alert] RobotShop Web Frontend Problem - Alert Description: \"resource.name=\"web-deployment\" severity=Minor resource.hostname=web-deployment type.eventType=\"robotshop\"\"", "description": "MySQL Database is unavailable in App.", "created_at": "2019-09-11T06:39:48.000Z", "updated_at": "2019-09-11T07:57:58.000Z", "resolved_at": "2019-09-11T07:57:58.000Z", "closed_at": "2019-09-11T07:57:58.000Z", "started_at": "2019-09-11T07:57:58.000Z", "business_duration_ms": 15347, "severity": 1, "priority": 2, "impact": 3, "state": "new", "source": { "source_name": "GitHub", "source_url": "https://pirsoscom.github.io/git-robotshop.html", "source_incident_id":  "ROB0000164", "source_application_id": "tokenizer124" }, "comments": [{ "comment_text": "MySQL Deployment was out of Memory. Resolved by increasing memory and restarting mysql pod: oc delete pod -n robot-shop $(oc get po -n robot-shop|grep mysql|awk '{print$1}')" }], "resolution": { "rca_id": "RCA004013505", "resolution_summary": "MySQL Deployment was out of Memory. Resolved by increasing memory and restarting mysql pod: oc delete pod -n robot-shop $(oc get po -n robot-shop|grep mysql|awk '{print$1}')" }, "features": [] }, "meta_features": []}
{ "application_group_id": "3mavyiwf", "application_id": "gj8nhgir", "timestamp": 1570221600, "utc_timestamp": "2019-10-04T20:40:00.038Z", "type": "incident", "incident": { "incident_id": "fed6b7bf-f741-49d1-ab36-5d04e9a5c005", "title": "[Alert] RobotShop Catalogue Problem - Alert Description: \"resource.name=\"catalogue-deployment\" severity=Critical resource.hostname=mysql type.eventType=\"robotshop\"\"", "description": "MySQL Database is unavailable in App.", "created_at": "2019-09-11T06:39:48.000Z", "updated_at": "2019-09-11T07:57:58.000Z", "resolved_at": "2019-09-11T07:57:58.000Z", "closed_at": "2019-09-11T07:57:58.000Z", "started_at": "2019-09-11T07:57:58.000Z", "business_duration_ms": 15347, "severity": 1, "priority": 2, "impact": 3, "state": "new", "source": { "source_name": "GitHub", "source_url": "https://pirsoscom.github.io/git-robotshop.html", "source_incident_id":  "ROB0000164", "source_application_id": "tokenizer124" }, "comments": [{ "comment_text": "MySQL Deployment was out of Memory. Resolved by increasing memory and restarting mysql pod: oc delete pod -n robot-shop $(oc get po -n robot-shop|grep mysql|awk '{print$1}')" }], "resolution": { "rca_id": "RCA004013505", "resolution_summary": "MySQL Deployment was out of Memory. Resolved by increasing memory and restarting mysql pod: oc delete pod -n robot-shop $(oc get po -n robot-shop|grep mysql|awk '{print$1}')" }, "features": [] }, "meta_features": []}
{ "application_group_id": "3mavyiwf", "application_id": "gj8nhgir", "timestamp": 1570221600, "utc_timestamp": "2019-10-04T20:40:00.038Z", "type": "incident", "incident": { "incident_id": "fed6b7bf-f741-49d1-ab36-5d04e9a5c005", "title": "[Alert] RobotShop Catalogue Problem - Alert Description: \"resource.name=\"catalogue-deployment\" severity=Major resource.hostname=catalogue type.eventType=\"robotshop\"\"", "description": "MySQL Database is unavailable in App.", "created_at": "2019-09-11T06:39:48.000Z", "updated_at": "2019-09-11T07:57:58.000Z", "resolved_at": "2019-09-11T07:57:58.000Z", "closed_at": "2019-09-11T07:57:58.000Z", "started_at": "2019-09-11T07:57:58.000Z", "business_duration_ms": 15347, "severity": 1, "priority": 2, "impact": 3, "state": "new", "source": { "source_name": "GitHub", "source_url": "https://pirsoscom.github.io/git-robotshop.html", "source_incident_id":  "ROB0000164", "source_application_id": "tokenizer124" }, "comments": [{ "comment_text": "MySQL Deployment was out of Memory. Resolved by increasing memory and restarting mysql pod: oc delete pod -n robot-shop $(oc get po -n robot-shop|grep mysql|awk '{print$1}')" }], "resolution": { "rca_id": "RCA004013505", "resolution_summary": "MySQL Deployment was out of Memory. Resolved by increasing memory and restarting mysql pod: oc delete pod -n robot-shop $(oc get po -n robot-shop|grep mysql|awk '{print$1}')" }, "features": [] }, "meta_features": []}
{ "application_group_id": "3mavyiwf", "application_id": "gj8nhgir", "timestamp": 1570221600, "utc_timestamp": "2019-10-04T20:40:00.038Z", "type": "incident", "incident": { "incident_id": "fed6b7bf-f741-49d1-ab36-5d04e9a5c005", "title": "[Alert] RobotShop Catalogue Problem - Alert Description: \"resource.name=\"catalogue-deployment\" severity=Critical resource.hostname=catalogue-db type.eventType=\"robotshop\"\"", "description": "MySQL Database is unavailable in App.", "created_at": "2019-09-11T06:39:48.000Z", "updated_at": "2019-09-11T07:57:58.000Z", "resolved_at": "2019-09-11T07:57:58.000Z", "closed_at": "2019-09-11T07:57:58.000Z", "started_at": "2019-09-11T07:57:58.000Z", "business_duration_ms": 15347, "severity": 1, "priority": 2, "impact": 3, "state": "new", "source": { "source_name": "GitHub", "source_url": "https://pirsoscom.github.io/git-robotshop.html", "source_incident_id":  "ROB0000164", "source_application_id": "tokenizer124" }, "comments": [{ "comment_text": "MySQL Deployment was out of Memory. Resolved by increasing memory and restarting mysql pod: oc delete pod -n robot-shop $(oc get po -n robot-shop|grep mysql|awk '{print$1}')" }], "resolution": { "rca_id": "RCA004013505", "resolution_summary": "MySQL Deployment was out of Memory. Resolved by increasing memory and restarting mysql pod: oc delete pod -n robot-shop $(oc get po -n robot-shop|grep mysql|awk '{print$1}')" }, "features": [] }, "meta_features": []}
{ "application_group_id": "3mavyiwf", "application_id": "gj8nhgir", "timestamp": 1570221600, "utc_timestamp": "2019-10-04T20:40:00.038Z", "type": "incident", "incident": { "incident_id": "fed6b7bf-f741-49d1-ab36-5d04e9a5c005", "title": "[Alert] RobotShop Ratings Problem - Alert Description: \"resource.name=\"ratings-deployment\" severity=Critical resource.hostname=user-db type.eventType=\"robotshop\"\"", "description": "MySQL Database is unavailable in App.", "created_at": "2019-09-11T06:39:48.000Z", "updated_at": "2019-09-11T07:57:58.000Z", "resolved_at": "2019-09-11T07:57:58.000Z", "closed_at": "2019-09-11T07:57:58.000Z", "started_at": "2019-09-11T07:57:58.000Z", "business_duration_ms": 15347, "severity": 1, "priority": 2, "impact": 3, "state": "new", "source": { "source_name": "GitHub", "source_url": "https://pirsoscom.github.io/git-robotshop.html", "source_incident_id":  "ROB0000164", "source_application_id": "tokenizer124" }, "comments": [{ "comment_text": "MySQL Deployment was out of Memory. Resolved by increasing memory and restarting mysql pod: oc delete pod -n robot-shop $(oc get po -n robot-shop|grep mysql|awk '{print$1}')" }], "resolution": { "rca_id": "RCA004013505", "resolution_summary": "MySQL Deployment was out of Memory. Resolved by increasing memory and restarting mysql pod: oc delete pod -n robot-shop $(oc get po -n robot-shop|grep mysql|awk '{print$1}')" }, "features": [] }, "meta_features": []}
{ "application_group_id": "3mavyiwf", "application_id": "gj8nhgir", "timestamp": 1570221600, "utc_timestamp": "2019-10-04T20:40:00.038Z", "type": "incident", "incident": { "incident_id": "fed6b7bf-f741-49d1-ab36-5d04e9a5c005", "title": "[Alert] RobotShop Ratings Problem - Alert Description: \"resource.name=\"ratings-deployment\" severity=Major resource.hostname=user type.eventType=\"robotshop\"\"", "description": "MySQL Database is unavailable in App.", "created_at": "2019-09-11T06:39:48.000Z", "updated_at": "2019-09-11T07:57:58.000Z", "resolved_at": "2019-09-11T07:57:58.000Z", "closed_at": "2019-09-11T07:57:58.000Z", "started_at": "2019-09-11T07:57:58.000Z", "business_duration_ms": 15347, "severity": 1, "priority": 2, "impact": 3, "state": "new", "source": { "source_name": "GitHub", "source_url": "https://pirsoscom.github.io/git-robotshop.html", "source_incident_id":  "ROB0000164", "source_application_id": "tokenizer124" }, "comments": [{ "comment_text": "MySQL Deployment was out of Memory. Resolved by increasing memory and restarting mysql pod: oc delete pod -n robot-shop $(oc get po -n robot-shop|grep mysql|awk '{print$1}')" }], "resolution": { "rca_id": "RCA004013505", "resolution_summary": "MySQL Deployment was out of Memory. Resolved by increasing memory and restarting mysql pod: oc delete pod -n robot-shop $(oc get po -n robot-shop|grep mysql|awk '{print$1}')" }, "features": [] }, "meta_features": []}
{ "application_group_id": "3mavyiwf", "application_id": "gj8nhgir", "timestamp": 1570221600, "utc_timestamp": "2019-10-04T20:40:00.038Z", "type": "incident", "incident": { "incident_id": "fed6b7bf-f741-49d1-ab36-5d04e9a5c005", "title": "[Alert] RobotShop Ratings Problem - Alert Description: \"resource.name=\"ratings-deployment\" severity=Critical resource.hostname=mysql type.eventType=\"robotshop\"\"", "description": "MySQL Database is unavailable in App.", "created_at": "2019-09-11T06:39:48.000Z", "updated_at": "2019-09-11T07:57:58.000Z", "resolved_at": "2019-09-11T07:57:58.000Z", "closed_at": "2019-09-11T07:57:58.000Z", "started_at": "2019-09-11T07:57:58.000Z", "business_duration_ms": 15347, "severity": 1, "priority": 2, "impact": 3, "state": "new", "source": { "source_name": "GitHub", "source_url": "https://pirsoscom.github.io/git-robotshop.html", "source_incident_id":  "ROB0000164", "source_application_id": "tokenizer124" }, "comments": [{ "comment_text": "MySQL Deployment was out of Memory. Resolved by increasing memory and restarting mysql pod: oc delete pod -n robot-shop $(oc get po -n robot-shop|grep mysql|awk '{print$1}')" }], "resolution": { "rca_id": "RCA004013505", "resolution_summary": "MySQL Deployment was out of Memory. Resolved by increasing memory and restarting mysql pod: oc delete pod -n robot-shop $(oc get po -n robot-shop|grep mysql|awk '{print$1}')" }, "features": [] }, "meta_features": []}
{ "application_group_id": "3mavyiwf", "application_id": "gj8nhgir", "timestamp": 1570221600, "utc_timestamp": "2019-10-04T20:40:00.038Z", "type": "incident", "incident": { "incident_id": "fed6b7bf-f741-49d1-ab36-5d04e9a5c005", "title": "[Instana] RobotShop call rate is too high - RobotShop call rate stays at a high level for an extended period of time", "description": "MySQL Database is unavailable in App.", "created_at": "2019-09-11T06:39:48.000Z", "updated_at": "2019-09-11T07:57:58.000Z", "resolved_at": "2019-09-11T07:57:58.000Z", "closed_at": "2019-09-11T07:57:58.000Z", "started_at": "2019-09-11T07:57:58.000Z", "business_duration_ms": 15347, "severity": 1, "priority": 2, "impact": 3, "state": "new", "source": { "source_name": "GitHub", "source_url": "https://pirsoscom.github.io/git-robotshop.html", "source_incident_id":  "ROB0000164", "source_application_id": "tokenizer124" }, "comments": [{ "comment_text": "MySQL Deployment was out of Memory. Resolved by increasing memory and restarting mysql pod: oc delete pod -n robot-shop $(oc get po -n robot-shop|grep mysql|awk '{print$1}')" }], "resolution": { "rca_id": "RCA004013505", "resolution_summary": "MySQL Deployment was out of Memory. Resolved by increasing memory and restarting mysql pod: oc delete pod -n robot-shop $(oc get po -n robot-shop|grep mysql|awk '{print$1}')" }, "features": [] }, "meta_features": []}
{ "application_group_id": "3mavyiwf", "application_id": "gj8nhgir", "timestamp": 1570221600, "utc_timestamp": "2019-10-04T20:40:00.038Z", "type": "incident", "incident": { "incident_id": "fed6b7bf-f741-49d1-ab36-5d04e9a5c005", "title": "[Instana] Sudden increase in the number of erroneous calls - This can be a sign of a problem on one side of the connection", "description": "MySQL Database is unavailable in App.", "created_at": "2019-09-11T06:39:48.000Z", "updated_at": "2019-09-11T07:57:58.000Z", "resolved_at": "2019-09-11T07:57:58.000Z", "closed_at": "2019-09-11T07:57:58.000Z", "started_at": "2019-09-11T07:57:58.000Z", "business_duration_ms": 15347, "severity": 1, "priority": 2, "impact": 3, "state": "new", "source": { "source_name": "GitHub", "source_url": "https://pirsoscom.github.io/git-robotshop.html", "source_incident_id":  "ROB0000164", "source_application_id": "tokenizer124" }, "comments": [{ "comment_text": "MySQL Deployment was out of Memory. Resolved by increasing memory and restarting mysql pod: oc delete pod -n robot-shop $(oc get po -n robot-shop|grep mysql|awk '{print$1}')" }], "resolution": { "rca_id": "RCA004013505", "resolution_summary": "MySQL Deployment was out of Memory. Resolved by increasing memory and restarting mysql pod: oc delete pod -n robot-shop $(oc get po -n robot-shop|grep mysql|awk '{print$1}')" }, "features": [] }, "meta_features": []}
{ "application_group_id": "3mavyiwf", "application_id": "gj8nhgir", "timestamp": 1570221600, "utc_timestamp": "2019-10-04T20:40:00.038Z", "type": "incident", "incident": { "incident_id": "fed6b7bf-f741-49d1-ab36-5d04e9a5c005", "title": "[Instana] RobotShop call rate is too high - RobotShop call rate stays at a high level for an extended period of time", "description": "MySQL Database is unavailable in App.", "created_at": "2019-09-11T06:39:48.000Z", "updated_at": "2019-09-11T07:57:58.000Z", "resolved_at": "2019-09-11T07:57:58.000Z", "closed_at": "2019-09-11T07:57:58.000Z", "started_at": "2019-09-11T07:57:58.000Z", "business_duration_ms": 15347, "severity": 1, "priority": 2, "impact": 3, "state": "new", "source": { "source_name": "GitHub", "source_url": "https://pirsoscom.github.io/git-robotshop.html", "source_incident_id":  "ROB0000164", "source_application_id": "tokenizer124" }, "comments": [{ "comment_text": "MySQL Deployment was out of Memory. Resolved by increasing memory and restarting mysql pod: oc delete pod -n robot-shop $(oc get po -n robot-shop|grep mysql|awk '{print$1}')" }], "resolution": { "rca_id": "RCA004013505", "resolution_summary": "MySQL Deployment was out of Memory. Resolved by increasing memory and restarting mysql pod: oc delete pod -n robot-shop $(oc get po -n robot-shop|grep mysql|awk '{print$1}')" }, "features": [] }, "meta_features": []}
{ "application_group_id": "3mavyiwf", "application_id": "gj8nhgir", "timestamp": 1570221600, "utc_timestamp": "2019-10-04T20:40:00.038Z", "type": "incident", "incident": { "incident_id": "fed6b7bf-f741-49d1-ab36-5d04e9a5c005", "title": "[Instana] RobotShop dudden increase in the number of erroneous calls - This can be a sign of a problem on one side of the connection", "description": "MySQL Database is unavailable in App.", "created_at": "2019-09-11T06:39:48.000Z", "updated_at": "2019-09-11T07:57:58.000Z", "resolved_at": "2019-09-11T07:57:58.000Z", "closed_at": "2019-09-11T07:57:58.000Z", "started_at": "2019-09-11T07:57:58.000Z", "business_duration_ms": 15347, "severity": 1, "priority": 2, "impact": 3, "state": "new", "source": { "source_name": "GitHub", "source_url": "https://pirsoscom.github.io/git-robotshop.html", "source_incident_id":  "ROB0000164", "source_application_id": "tokenizer124" }, "comments": [{ "comment_text": "MySQL Deployment was out of Memory. Resolved by increasing memory and restarting mysql pod: oc delete pod -n robot-shop $(oc get po -n robot-shop|grep mysql|awk '{print$1}')" }], "resolution": { "rca_id": "RCA004013505", "resolution_summary": "MySQL Deployment was out of Memory. Resolved by increasing memory and restarting mysql pod: oc delete pod -n robot-shop $(oc get po -n robot-shop|grep mysql|awk '{print$1}')" }, "features": [] }, "meta_features": []}
{ "application_group_id": "3mavyiwf", "application_id": "gj8nhgir", "timestamp": 1570221600, "utc_timestamp": "2019-10-04T20:40:00.038Z", "type": "incident", "incident": { "incident_id": "fed6b7bf-f741-49d1-ab36-5d04e9a5c005", "title": "[Instana] RobotShop call rate is too high - RobotShop call rate stays at a high level for an extended period of time", "description": "MySQL Database is unavailable in App.", "created_at": "2019-09-11T06:39:48.000Z", "updated_at": "2019-09-11T07:57:58.000Z", "resolved_at": "2019-09-11T07:57:58.000Z", "closed_at": "2019-09-11T07:57:58.000Z", "started_at": "2019-09-11T07:57:58.000Z", "business_duration_ms": 15347, "severity": 1, "priority": 2, "impact": 3, "state": "new", "source": { "source_name": "GitHub", "source_url": "https://pirsoscom.github.io/git-robotshop.html", "source_incident_id":  "ROB0000164", "source_application_id": "tokenizer124" }, "comments": [{ "comment_text": "MySQL Deployment was out of Memory. Resolved by increasing memory and restarting mysql pod: oc delete pod -n robot-shop $(oc get po -n robot-shop|grep mysql|awk '{print$1}')" }], "resolution": { "rca_id": "RCA004013505", "resolution_summary": "MySQL Deployment was out of Memory. Resolved by increasing memory and restarting mysql pod: oc delete pod -n robot-shop $(oc get po -n robot-shop|grep mysql|awk '{print$1}')" }, "features": [] }, "meta_features": []}
{ "application_group_id": "3mavyiwf", "application_id": "gj8nhgir", "timestamp": 1570221600, "utc_timestamp": "2019-10-04T20:40:00.038Z", "type": "incident", "incident": { "incident_id": "fed6b7bf-f741-49d1-ab36-5d04e9a5c005", "title": "[Instana] RobotShop sudden increase in the number of erroneous calls - This can be a sign of a problem on one side of the connection", "description": "MySQL Database is unavailable in App.", "created_at": "2019-09-11T06:39:48.000Z", "updated_at": "2019-09-11T07:57:58.000Z", "resolved_at": "2019-09-11T07:57:58.000Z", "closed_at": "2019-09-11T07:57:58.000Z", "started_at": "2019-09-11T07:57:58.000Z", "business_duration_ms": 15347, "severity": 1, "priority": 2, "impact": 3, "state": "new", "source": { "source_name": "GitHub", "source_url": "https://pirsoscom.github.io/git-robotshop.html", "source_incident_id":  "ROB0000164", "source_application_id": "tokenizer124" }, "comments": [{ "comment_text": "MySQL Deployment was out of Memory. Resolved by increasing memory and restarting mysql pod: oc delete pod -n robot-shop $(oc get po -n robot-shop|grep mysql|awk '{print$1}')" }], "resolution": { "rca_id": "RCA004013505", "resolution_summary": "MySQL Deployment was out of Memory. Resolved by increasing memory and restarting mysql pod: oc delete pod -n robot-shop $(oc get po -n robot-shop|grep mysql|awk '{print$1}')" }, "features": [] }, "meta_features": []}
{ "application_group_id": "3mavyiwf", "application_id": "gj8nhgir", "timestamp": 1570221600, "utc_timestamp": "2019-10-04T20:40:00.038Z", "type": "incident", "incident": { "incident_id": "fed6b7bf-f741-49d1-ab36-5d04e9a5c005", "title": "Alert Name: \"RobotShopFrontendProblem\" Alert Description: \"resource.name=\"web-deployment\" severity=Minor resource.hostname=web-deployment type.eventType=\"robotshop\"\"", "description": "MySQL Database is unavailable in App.", "created_at": "2019-09-11T06:39:48.000Z", "updated_at": "2019-09-11T07:57:58.000Z", "resolved_at": "2019-09-11T07:57:58.000Z", "closed_at": "2019-09-11T07:57:58.000Z", "started_at": "2019-09-11T07:57:58.000Z", "business_duration_ms": 15347, "severity": 1, "priority": 2, "impact": 3, "state": "new", "source": { "source_name": "GitHub", "source_url": "https://pirsoscom.github.io/git-robotshop.html", "source_incident_id":  "ROB0000164", "source_application_id": "tokenizer124" }, "comments": [{ "comment_text": "MySQL Deployment was out of Memory. Resolved by increasing memory and restarting mysql pod: oc delete pod -n robot-shop $(oc get po -n robot-shop|grep mysql|awk '{print$1}')" }], "resolution": { "rca_id": "RCA004013505", "resolution_summary": "MySQL Deployment was out of Memory. Resolved by increasing memory and restarting mysql pod: oc delete pod -n robot-shop $(oc get po -n robot-shop|grep mysql|awk '{print$1}')" }, "features": [] }, "meta_features": []}
{"application_group_id": "3mavyiwf","application_id": "sszctxgk","timestamp": 1570221600,"utc_timestamp": "2019-10-04T20:40:00.038Z","type": "incident","incident": {"incident_id": "fed6b7bf-f741-49d1-ab36-5d04e9a5c128","title": "[Git] Commit in repository robot-shop by Niklaus Hirt on file robot-shop.yaml - New Memory Limits","description": "Git Commit.","created_at": "2019-09-11T06:39:48.000Z","updated_at": "2019-09-11T07:57:58.000Z","resolved_at": "2019-09-11T07:57:58.000Z","closed_at": "2019-09-11T07:57:58.000Z","started_at": "2019-09-11T07:57:58.000Z","business_duration_ms": 15347,"severity": 1,"priority": 2,"impact": 3,"state": "new","source": {"source_name": "GitHub","source_url":"https://pirsoscom.github.io/git-robotshop.html","source_incident_id": "KUB00000606","source_application_id": "tokenizer124"},"comments": [{"comment_text":"Rebooted Pod."}],"related_incidents":[{"source_incident_id":"KUB000005053","relationship":"parent"}],"resolution": {"rca_id": "RCA00f013547","resolution_summary": "The problem was resolved by rebooting the pod."},"features": []},"meta_features": []}
{"application_group_id": "3mavyiwf","application_id": "sszctxgk","timestamp": 1570221600,"utc_timestamp": "2019-10-04T20:40:00.038Z","type": "incident","incident": {"incident_id": "fed6b7bf-f741-49d1-ab36-5d04e9a5c128","title": "[Instana] MySQL - change detected - The value **resources/limits** has changed","description": "MySQL - change detected.","created_at": "2019-09-11T06:39:48.000Z","updated_at": "2019-09-11T07:57:58.000Z","resolved_at": "2019-09-11T07:57:58.000Z","closed_at": "2019-09-11T07:57:58.000Z","started_at": "2019-09-11T07:57:58.000Z","business_duration_ms": 15347,"severity": 1,"priority": 2,"impact": 3,"state": "new","source": {"source_name": "GitHub","source_url":"https://pirsoscom.github.io/git-robotshop.html","source_incident_id": "KUB00000606","source_application_id": "tokenizer124"},"comments": [{"comment_text":"Rebooted Pod."}],"related_incidents":[{"source_incident_id":"KUB000005053","relationship":"parent"}],"resolution": {"rca_id": "RCA00f013547","resolution_summary": "The problem was resolved by rebooting the pod."},"features": []},"meta_features": []}
{"application_group_id": "3mavyiwf","application_id": "sszctxgk","timestamp": 1570221600,"utc_timestamp": "2019-10-04T20:40:00.038Z","type": "incident","incident": {"incident_id": "fed6b7bf-f741-49d1-ab36-5d04e9a5c128","title": "[Security] MySQL - K8s Deployment Modified","description": "MySQL - K8s Deployment Modified.","created_at": "2019-09-11T06:39:48.000Z","updated_at": "2019-09-11T07:57:58.000Z","resolved_at": "2019-09-11T07:57:58.000Z","closed_at": "2019-09-11T07:57:58.000Z","started_at": "2019-09-11T07:57:58.000Z","business_duration_ms": 15347,"severity": 1,"priority": 2,"impact": 3,"state": "new","source": {"source_name": "GitHub","source_url":"https://pirsoscom.github.io/git-robotshop.html","source_incident_id": "KUB00000606","source_application_id": "tokenizer124"},"comments": [{"comment_text":"Rebooted Pod."}],"related_incidents":[{"source_incident_id":"KUB000005053","relationship":"parent"}],"resolution": {"rca_id": "RCA00f013547","resolution_summary": "The problem was resolved by rebooting the pod."},"features": []},"meta_features": []}
{"application_group_id": "3mavyiwf","application_id": "sszctxgk","timestamp": 1570221600,"utc_timestamp": "2019-10-04T20:40:00.038Z","type": "incident","incident": {"incident_id": "fed6b7bf-f741-49d1-ab36-5d04e9a5c128","title": "[Security] MySQL K8s Pod Created","description": "MySQL K8s Pod Created.","created_at": "2019-09-11T06:39:48.000Z","updated_at": "2019-09-11T07:57:58.000Z","resolved_at": "2019-09-11T07:57:58.000Z","closed_at": "2019-09-11T07:57:58.000Z","started_at": "2019-09-11T07:57:58.000Z","business_duration_ms": 15347,"severity": 1,"priority": 2,"impact": 3,"state": "new","source": {"source_name": "GitHub","source_url":"https://pirsoscom.github.io/git-robotshop.html","source_incident_id": "KUB00000606","source_application_id": "tokenizer124"},"comments": [{"comment_text":"Rebooted Pod."}],"related_incidents":[{"source_incident_id":"KUB000005053","relationship":"parent"}],"resolution": {"rca_id": "RCA00f013547","resolution_summary": "The problem was resolved by rebooting the pod."},"features": []},"meta_features": []}
{"application_group_id": "3mavyiwf","application_id": "sszctxgk","timestamp": 1570221600,"utc_timestamp": "2019-10-04T20:40:00.038Z","type": "incident","incident": {"incident_id": "fed6b7bf-f741-49d1-ab36-5d04e9a5c128","title": "[Predictive] MySQL memory peak usage anomaly","description": "MySQL memory peak usage anomaly.","created_at": "2019-09-11T06:39:48.000Z","updated_at": "2019-09-11T07:57:58.000Z","resolved_at": "2019-09-11T07:57:58.000Z","closed_at": "2019-09-11T07:57:58.000Z","started_at": "2019-09-11T07:57:58.000Z","business_duration_ms": 15347,"severity": 1,"priority": 2,"impact": 3,"state": "new","source": {"source_name": "GitHub","source_url":"https://pirsoscom.github.io/git-robotshop.html","source_incident_id": "KUB00000606","source_application_id": "tokenizer124"},"comments": [{"comment_text":"Rebooted Pod."}],"related_incidents":[{"source_incident_id":"KUB000005053","relationship":"parent"}],"resolution": {"rca_id": "RCA00f013547","resolution_summary": "The problem was resolved by rebooting the pod."},"features": []},"meta_features": []}
{"application_group_id": "3mavyiwf","application_id": "sszctxgk","timestamp": 1570221600,"utc_timestamp": "2019-10-04T20:40:00.038Z","type": "incident","incident": {"incident_id": "fed6b7bf-f741-49d1-ab36-5d04e9a5c128","title": "[Synthetic] Robotshop Homepage - Functional verification failed","description": "Robotshop Homepage - Functional verification failed.","created_at": "2019-09-11T06:39:48.000Z","updated_at": "2019-09-11T07:57:58.000Z","resolved_at": "2019-09-11T07:57:58.000Z","closed_at": "2019-09-11T07:57:58.000Z","started_at": "2019-09-11T07:57:58.000Z","business_duration_ms": 15347,"severity": 1,"priority": 2,"impact": 3,"state": "new","source": {"source_name": "GitHub","source_url":"https://pirsoscom.github.io/git-robotshop.html","source_incident_id": "KUB00000606","source_application_id": "tokenizer124"},"comments": [{"comment_text":"Rebooted Pod."}],"related_incidents":[{"source_incident_id":"KUB000005053","relationship":"parent"}],"resolution": {"rca_id": "RCA00f013547","resolution_summary": "The problem was resolved by rebooting the pod."},"features": []},"meta_features": []}
{"application_group_id": "3mavyiwf","application_id": "sszctxgk","timestamp": 1570221600,"utc_timestamp": "2019-10-04T20:40:00.038Z","type": "incident","incident": {"incident_id": "fed6b7bf-f741-49d1-ab36-5d04e9a5c128","title": "[Log] Catalogue - Alert Description: resource.name=catalogue (Error: unable to contact http://ratings:9080/ratings got status of 503)","description": "Catalogue Alert Triggered.","created_at": "2019-09-11T06:39:48.000Z","updated_at": "2019-09-11T07:57:58.000Z","resolved_at": "2019-09-11T07:57:58.000Z","closed_at": "2019-09-11T07:57:58.000Z","started_at": "2019-09-11T07:57:58.000Z","business_duration_ms": 15347,"severity": 1,"priority": 2,"impact": 3,"state": "new","source": {"source_name": "GitHub","source_url":"https://pirsoscom.github.io/git-robotshop.html","source_incident_id": "KUB00000606","source_application_id": "tokenizer124"},"comments": [{"comment_text":"Rebooted Pod."}],"related_incidents":[{"source_incident_id":"KUB000005053","relationship":"parent"}],"resolution": {"rca_id": "RCA00f013547","resolution_summary": "The problem was resolved by rebooting the pod."},"features": []},"meta_features": []}
{"application_group_id": "3mavyiwf","application_id": "sszctxgk","timestamp": 1570221600,"utc_timestamp": "2019-10-04T20:40:00.038Z","type": "incident","incident": {"incident_id": "fed6b7bf-f741-49d1-ab36-5d04e9a5c128","title": "[Log] Ratings - Alert Description: resource.name=ratings  (Error: unable to contact MYSQL failed with status code 500)","description": "Ratings Alert Triggered.","created_at": "2019-09-11T06:39:48.000Z","updated_at": "2019-09-11T07:57:58.000Z","resolved_at": "2019-09-11T07:57:58.000Z","closed_at": "2019-09-11T07:57:58.000Z","started_at": "2019-09-11T07:57:58.000Z","business_duration_ms": 15347,"severity": 1,"priority": 2,"impact": 3,"state": "new","source": {"source_name": "GitHub","source_url":"https://pirsoscom.github.io/git-robotshop.html","source_incident_id": "KUB00000606","source_application_id": "tokenizer124"},"comments": [{"comment_text":"Rebooted Pod."}],"related_incidents":[{"source_incident_id":"KUB000005053","relationship":"parent"}],"resolution": {"rca_id": "RCA00f013547","resolution_summary": "The problem was resolved by rebooting the pod."},"features": []},"meta_features": []}
{"application_group_id": "3mavyiwf","application_id": "sszctxgk","timestamp": 1570221600,"utc_timestamp": "2019-10-04T20:40:00.038Z","type": "incident","incident": {"incident_id": "fed6b7bf-f741-49d1-ab36-5d04e9a5c128","title": "[Predictive] Ratings - Transactions anomaly","description": "Ratings - Transactions anomaly.","created_at": "2019-09-11T06:39:48.000Z","updated_at": "2019-09-11T07:57:58.000Z","resolved_at": "2019-09-11T07:57:58.000Z","closed_at": "2019-09-11T07:57:58.000Z","started_at": "2019-09-11T07:57:58.000Z","business_duration_ms": 15347,"severity": 1,"priority": 2,"impact": 3,"state": "new","source": {"source_name": "GitHub","source_url":"https://pirsoscom.github.io/git-robotshop.html","source_incident_id": "KUB00000606","source_application_id": "tokenizer124"},"comments": [{"comment_text":"Rebooted Pod."}],"related_incidents":[{"source_incident_id":"KUB000005053","relationship":"parent"}],"resolution": {"rca_id": "RCA00f013547","resolution_summary": "The problem was resolved by rebooting the pod."},"features": []},"meta_features": []}
{"application_group_id": "3mavyiwf","application_id": "sszctxgk","timestamp": 1570221600,"utc_timestamp": "2019-10-04T20:40:00.038Z","type": "incident","incident": {"incident_id": "fed6b7bf-f741-49d1-ab36-5d04e9a5c128","title": "[Instana] MySQL - available replicas is less than desired replicas - Check conditions and error events","description": "MySQL - available replicas is less than desired replicas.","created_at": "2019-09-11T06:39:48.000Z","updated_at": "2019-09-11T07:57:58.000Z","resolved_at": "2019-09-11T07:57:58.000Z","closed_at": "2019-09-11T07:57:58.000Z","started_at": "2019-09-11T07:57:58.000Z","business_duration_ms": 15347,"severity": 1,"priority": 2,"impact": 3,"state": "new","source": {"source_name": "GitHub","source_url":"https://pirsoscom.github.io/git-robotshop.html","source_incident_id": "KUB00000606","source_application_id": "tokenizer124"},"comments": [{"comment_text":"Rebooted Pod."}],"related_incidents":[{"source_incident_id":"KUB000005053","relationship":"parent"}],"resolution": {"rca_id": "RCA00f013547","resolution_summary": "The problem was resolved by rebooting the pod."},"features": []},"meta_features": []}
{"application_group_id": "3mavyiwf","application_id": "sszctxgk","timestamp": 1570221600,"utc_timestamp": "2019-10-04T20:40:00.038Z","type": "incident","incident": {"incident_id": "fed6b7bf-f741-49d1-ab36-5d04e9a5c128","title": "[Instana] Robotshop Homepage call rate is too high- Robotshop call rate stays at a high level for an extended period of time","description": "Robotshop Homepage call rate is too high.","created_at": "2019-09-11T06:39:48.000Z","updated_at": "2019-09-11T07:57:58.000Z","resolved_at": "2019-09-11T07:57:58.000Z","closed_at": "2019-09-11T07:57:58.000Z","started_at": "2019-09-11T07:57:58.000Z","business_duration_ms": 15347,"severity": 1,"priority": 2,"impact": 3,"state": "new","source": {"source_name": "GitHub","source_url":"https://pirsoscom.github.io/git-robotshop.html","source_incident_id": "KUB00000606","source_application_id": "tokenizer124"},"comments": [{"comment_text":"Rebooted Pod."}],"related_incidents":[{"source_incident_id":"KUB000005053","relationship":"parent"}],"resolution": {"rca_id": "RCA00f013547","resolution_summary": "The problem was resolved by rebooting the pod."},"features": []},"meta_features": []}
{"application_group_id": "3mavyiwf","application_id": "sszctxgk","timestamp": 1570221600,"utc_timestamp": "2019-10-04T20:40:00.038Z","type": "incident","incident": {"incident_id": "fed6b7bf-f741-49d1-ab36-5d04e9a5c128","title": "Users are not able to access Discovery and Conversation in EU","description": "Unable to connect to email using my laptop.","created_at": "2019-09-11T06:39:48.000Z","updated_at": "2019-09-11T07:57:58.000Z","resolved_at": "2019-09-11T07:57:58.000Z","closed_at": "2019-09-11T07:57:58.000Z","started_at": "2019-09-11T07:57:58.000Z","business_duration_ms": 15347,"severity": 1,"priority": 2,"impact": 3,"state": "new","source": {"source_name": "GitHub","source_url":"https://pirsoscom.github.io/git-robotshop.html","source_incident_id": "KUB00000601","source_application_id": "tokenizer124"},"comments": [{"comment_text":"Rebooted it."}],"related_incidents":[{"source_incident_id":"KUB00000591","relationship":"parent"}],"resolution": {"rca_id": "RCAa00013547","resolution_summary": "The problem was resolved by rebooting the laptop."},"features": []},"meta_features": []}
{"application_group_id": "3mavyiwf","application_id": "sszctxgk","timestamp": 1570221600,"utc_timestamp": "2019-10-04T20:40:00.038Z","type": "incident","incident": {"incident_id": "fed6b7bf-f741-49d1-ab36-5d04e9a5c129","title": "Alert Name: MyEvent Alert Description: resource.name","description": "Unable to connect to email using my laptop.","created_at": "2019-09-11T06:39:48.000Z","updated_at": "2019-09-11T07:57:58.000Z","resolved_at": "2019-09-11T07:57:58.000Z","closed_at": "2019-09-11T07:57:58.000Z","started_at": "2019-09-11T07:57:58.000Z","business_duration_ms": 15347,"severity": 1,"priority": 2,"impact": 3,"state": "new","source": {"source_name": "GitHub","source_url":"https://pirsoscom.github.io/git-robotshop.html","source_incident_id": "KUB00000602","source_application_id": "tokenizer124"},"comments": [{"comment_text":"Rebooted it."}],"related_incidents":[{"source_incident_id":"KUB00000592","relationship":"parent"}],"resolution": {"rca_id": "RCA0001s3547","resolution_summary": "The problem was resolved by rebooting the laptop."},"features": []},"meta_features": []}
{ "application_group_id": "3mavyiwf", "application_id": "gj8nhgir", "timestamp": 1570221600, "utc_timestamp": "2019-10-04T20:40:00.038Z", "type": "incident", "incident": { "incident_id": "fed6b7bf-f741-49d1-ab36-5d04e9a5c005", "title": "<*> stdout F <*> - - [<*>/May/<*>:<*>:<*>:<*> <*>] <*> ", "description": "MySQL Database is unavailable in App.", "created_at": "2019-09-11T06:39:48.000Z", "updated_at": "2019-09-11T07:57:58.000Z", "resolved_at": "2019-09-11T07:57:58.000Z", "closed_at": "2019-09-11T07:57:58.000Z", "started_at": "2019-09-11T07:57:58.000Z", "business_duration_ms": 15347, "severity": 1, "priority": 2, "impact": 3, "state": "new", "source": { "source_name": "GitHub", "source_url": "https://pirsoscom.github.io/git-robotshop.html", "source_incident_id":  "ROB0000164", "source_application_id": "tokenizer124" }, "comments": [{ "comment_text": "MySQL Deployment was out of Memory. Resolved by increasing memory and restarting mysql pod: oc delete pod -n robot-shop $(oc get po -n robot-shop|grep mysql|awk '{print$1}')" }], "resolution": { "rca_id": "RCA004013505", "resolution_summary": "MySQL Deployment was out of Memory. Resolved by increasing memory and restarting mysql pod: oc delete pod -n robot-shop $(oc get po -n robot-shop|grep mysql|awk '{print$1}')" }, "features": [] }, "meta_features": []}
{"application_group_id": "3mavyiwf","application_id": "sszctxgk","timestamp": 1570221600,"utc_timestamp": "2019-10-04T20:40:00.038Z","type": "incident","incident": {"incident_id": "fed6b7bf-f741-49d1-ab36-5d04e9a5c128","title": "Turbonomic] Container Resize - Controller Resize - Resize UP VMem Limit from 50 MB to 328 MB in Container Spec mysql","description": "MySQL memory peak usage anomaly.","created_at": "2019-09-11T06:39:48.000Z","updated_at": "2019-09-11T07:57:58.000Z","resolved_at": "2019-09-11T07:57:58.000Z","closed_at": "2019-09-11T07:57:58.000Z","started_at": "2019-09-11T07:57:58.000Z","business_duration_ms": 15347,"severity": 1,"priority": 2,"impact": 3,"state": "new","source": {"source_name": "GitHub","source_url":"https://pirsoscom.github.io/git-robotshop.html","source_incident_id": "KUB00000606","source_application_id": "tokenizer124"},"comments": [{"comment_text":"Rebooted Pod."}],"related_incidents":[{"source_incident_id":"KUB000005053","relationship":"parent"}],"resolution": {"rca_id": "RCA00f013547","resolution_summary": "MySQL Deployment was out of Memory. Resolved by increasing memory and restarting mysql pod: oc delete pod -n robot-shop $(oc get po -n robot-shop|grep mysql|awk '{print$1}')"},"features": []},"meta_features": []}
